comun_db.py
comun_db-0.2.dist-info/METADATA
comun_db-0.2.dist-info/WHEEL
comun_db-0.2.dist-info/top_level.txt
comun_db-0.2.dist-info/RECORD
