Metadata-Version: 2.1
Name: comun-db
Version: 0.2
Summary: UNKNOWN
Home-page: UNKNOWN
License: UNKNOWN
Platform: UNKNOWN
Requires-Dist: pyodbc
